aslabs/cloud_structlog/__init__.py
aslabs/cloud_structlog/cloud_json_renderer.py
aslabs/cloud_structlog/logger_config.py
aslabs/cloud_structlog/logger_factory.py
aslabs_cloud_structlog-0.0.3.dist-info/WHEEL
aslabs_cloud_structlog-0.0.3.dist-info/METADATA
aslabs_cloud_structlog-0.0.3.dist-info/RECORD
